fusnmp/Singleton.py
fusnmp/__init__.py
fusnmp/constants.py
fusnmp/snmp.py
fusnmp-1.0.3.dist-info/LICENSE.txt
fusnmp-1.0.3.dist-info/METADATA
fusnmp-1.0.3.dist-info/WHEEL
fusnmp-1.0.3.dist-info/top_level.txt
fusnmp-1.0.3.dist-info/RECORD
