Metadata-Version: 2.1
Name: fusnmp
Version: 1.0.3
Summary: A small but complete NetSNMP ctypes wrapper.
Home-page: http://github.com/jdugan1024/fusnmp/
Author: Jon M. Dugan
Author-email: jdugan@x1024.net
License: GPL
Keywords: snmp networking
Platform: UNKNOWN
Classifier: Development Status :: 7 - Inactive
Classifier: Environment :: Console
Classifier: Intended Audience :: Developers
Classifier: Programming Language :: Python
Classifier: License :: OSI Approved :: GNU General Public License (GPL)
Classifier: Topic :: Internet
Classifier: Operating System :: POSIX
